pub_lake/__init__.py
pub_lake/__main__.py
pub_lake/config.py
pub_lake/pub_lake.py
pub_lake/cli/__init__.py
pub_lake/cli/preprints.py
pub_lake/elt/__init__.py
pub_lake/elt/pipeline.py
pub_lake/elt/extract/__init__.py
pub_lake/elt/extract/biorxiv.py
pub_lake/elt/extract/openalex.py
pub_lake/elt/load/__init__.py
pub_lake/elt/load/bronze.py
pub_lake/elt/transform/__init__.py
pub_lake/elt/transform/gold.py
pub_lake/elt/transform/silver.py
pub_lake/interface/__init__.py
pub_lake/interface/preprints.py
pub_lake/models/__init__.py
pub_lake/models/preprints.py
pub_lake/models/schema.py
pub_lake-0.1.1.dist-info/licenses/LICENSE
pub_lake-0.1.1.dist-info/METADATA
pub_lake-0.1.1.dist-info/WHEEL
pub_lake-0.1.1.dist-info/entry_points.txt
pub_lake-0.1.1.dist-info/top_level.txt
pub_lake-0.1.1.dist-info/RECORD
