Metadata-Version: 2.4
Name: pub-lake
Version: 0.1.1
Summary: Aggregate publication metadata from bioRxiv, OpenAlex, and more.
Author-email: Thomas Eidens <thomas.eidens@embo.org>
Maintainer-email: Thomas Eidens <thomas.eidens@embo.org>
License-Expression: MIT
Project-URL: bugs, https://github.com/source-data/pub-lake/issues
Project-URL: changelog, https://github.com/source-data/pub-lake/blob/main/HISTORY.md
Project-URL: homepage, https://github.com/source-data/pub-lake
Classifier: Programming Language :: Python :: 3.10
Classifier: Programming Language :: Python :: 3.11
Classifier: Programming Language :: Python :: 3.12
Classifier: Programming Language :: Python :: 3.13
Classifier: Operating System :: OS Independent
Classifier: Development Status :: 4 - Beta
Classifier: Intended Audience :: Developers
Classifier: Intended Audience :: Science/Research
Classifier: Topic :: Scientific/Engineering :: Information Analysis
Requires-Python: >=3.10
License-File: LICENSE
Requires-Dist: pandas>=2.3.3
Requires-Dist: pyalex>=0.18
Requires-Dist: pydantic>=2.12.3
Requires-Dist: requests>=2.32.5
Requires-Dist: sqlalchemy>=2.0.44
Requires-Dist: sqlalchemy-utc>=0.14.0
Requires-Dist: tenacity>=9.1.2
Requires-Dist: tqdm>=4.67.1
Requires-Dist: typer-slim>=0.20.0
Dynamic: license-file
